roboemotion/__init__.py
roboemotion/move.py
roboemotion/robo_emotion_config.json
roboemotion/util.py
roboemotion-1.0.5.dist-info/DESCRIPTION.rst
roboemotion-1.0.5.dist-info/METADATA
roboemotion-1.0.5.dist-info/RECORD
roboemotion-1.0.5.dist-info/WHEEL
roboemotion-1.0.5.dist-info/metadata.json
roboemotion-1.0.5.dist-info/top_level.txt
