Metadata-Version: 2.0
Name: roboemotion
Version: 1.0.5
Summary: emotion expressing for robotic arms
Home-page: https://github.com/chengjovy/RoboEmotion
Author: Jovy Cheng
Author-email: chengjovy83@gmail.com
License: MIT
Platform: UNKNOWN
Requires-Dist: serial
